{
  "uid": "dpos-single-validator-generated",
  "title": "DPoS Single Validator Generated",
  "description": "Detailed view of a single DPoS validator performance and statistics - Generated by thorflux dashgen",
  "tags": [
    "generated",
    "vechain",
    "thorflux",
    "dpos",
    "validator",
    "single"
  ],
  "timezone": "browser",
  "editable": true,
  "graphTooltip": 0,
  "time": {
    "from": "now-24h",
    "to": "now"
  },
  "fiscalYearStartMonth": 0,
  "refresh": "30s",
  "schemaVersion": 39,
  "panels": [
    {
      "type": "text",
      "title": "",
      "transparent": true,
      "datasource": {
        "type": "grafana",
        "uid": "-- Grafana --"
      },
      "gridPos": {
        "h": 2,
        "w": 24,
        "x": 0,
        "y": 0
      },
      "options": {
        "mode": "html",
        "content": "\u003cdiv style=\"display: flex; align-items: center; justify-content: center; width: 100%; height: 48px; padding: 0 16px; border-radius: 10px; background: linear-gradient(90deg, #02254A 0%, #03422C 100%); color: #e9fff9; font: 600 36px/1.1 Inter, system-ui, -apple-system, Segoe UI, Roboto, Arial, sans-serif; letter-spacing: .08em; text-transform: uppercase; text-align: center; box-shadow: inset 0 0 0 1px rgba(255, 255, 255, .06), 0 6px 20px rgba(0, 0, 0, .35);\"\u003eDPoS Single Validator\u003c/div\u003e"
      }
    },
    {
      "type": "stat",
      "targets": [
        {
          "refId": "A",
          "queryType": "flux",
          "datasource": {
            "type": "influxdb",
            "uid": "B87265B08D314AF"
          },
          "query": "from(bucket: \"${bucket}\")\n  |\u003e range(start: v.timeRangeStart, stop: v.timeRangeStop)\n  |\u003e filter(fn: (r) =\u003e r[\"_measurement\"] == \"validator_status\")\n  |\u003e filter(fn: (r) =\u003e r[\"validator_address\"] == \"${validator}\")\n  |\u003e filter(fn: (r) =\u003e r[\"_field\"] == \"is_active\")\n  |\u003e group()\n  |\u003e last()\n  |\u003e yield(name: \"_value\")"
        }
      ],
      "title": "Validator Status",
      "description": "Current status of the selected validator",
      "transparent": false,
      "datasource": {
        "type": "influxdb",
        "uid": "B87265B08D314AF"
      },
      "gridPos": {
        "h": 9,
        "w": 12,
        "x": 0,
        "y": 2
      },
      "options": {
        "graphMode": "area",
        "colorMode": "value",
        "justifyMode": "auto",
        "textMode": "auto",
        "wideLayout": true,
        "showPercentChange": false,
        "reduceOptions": {
          "calcs": [
            "lastNotNull"
          ],
          "fields": "/.*/"
        },
        "percentChangeColorMode": "standard",
        "orientation": ""
      }
    },
    {
      "type": "stat",
      "targets": [
        {
          "refId": "A",
          "queryType": "flux",
          "datasource": {
            "type": "influxdb",
            "uid": "B87265B08D314AF"
          },
          "query": "from(bucket: \"${bucket}\")\n  |\u003e range(start: v.timeRangeStart, stop: v.timeRangeStop)\n  |\u003e filter(fn: (r) =\u003e r[\"_measurement\"] == \"validator_stakes\")\n  |\u003e filter(fn: (r) =\u003e r[\"validator_address\"] == \"${validator}\")\n  |\u003e filter(fn: (r) =\u003e r[\"_field\"] == \"total_stake\")\n  |\u003e group()\n  |\u003e last()\n  |\u003e yield(name: \"_value\")"
        }
      ],
      "title": "Total Stake",
      "description": "Total amount of VET staked to this validator",
      "transparent": false,
      "datasource": {
        "type": "influxdb",
        "uid": "B87265B08D314AF"
      },
      "gridPos": {
        "h": 9,
        "w": 12,
        "x": 12,
        "y": 2
      },
      "options": {
        "graphMode": "area",
        "colorMode": "value",
        "justifyMode": "auto",
        "textMode": "auto",
        "wideLayout": true,
        "showPercentChange": false,
        "reduceOptions": {
          "calcs": [
            "lastNotNull"
          ],
          "fields": "/.*/"
        },
        "percentChangeColorMode": "standard",
        "orientation": ""
      },
      "fieldConfig": {
        "defaults": {
          "unit": "short"
        },
        "overrides": null
      }
    },
    {
      "type": "stat",
      "targets": [
        {
          "refId": "A",
          "queryType": "flux",
          "datasource": {
            "type": "influxdb",
            "uid": "B87265B08D314AF"
          },
          "query": "from(bucket: \"${bucket}\")\n  |\u003e range(start: v.timeRangeStart, stop: v.timeRangeStop)\n  |\u003e filter(fn: (r) =\u003e r[\"_measurement\"] == \"validator_delegations\")\n  |\u003e filter(fn: (r) =\u003e r[\"validator_address\"] == \"${validator}\")\n  |\u003e group(columns: [\"delegator_address\"])\n  |\u003e count()\n  |\u003e group()\n  |\u003e sum()"
        }
      ],
      "title": "Active Delegators",
      "description": "Number of active delegators for this validator",
      "transparent": false,
      "datasource": {
        "type": "influxdb",
        "uid": "B87265B08D314AF"
      },
      "gridPos": {
        "h": 9,
        "w": 12,
        "x": 0,
        "y": 11
      },
      "options": {
        "graphMode": "area",
        "colorMode": "value",
        "justifyMode": "auto",
        "textMode": "auto",
        "wideLayout": true,
        "showPercentChange": false,
        "reduceOptions": {
          "calcs": [
            "lastNotNull"
          ],
          "fields": "/.*/"
        },
        "percentChangeColorMode": "standard",
        "orientation": ""
      }
    },
    {
      "type": "timeseries",
      "targets": [
        {
          "refId": "A",
          "queryType": "flux",
          "datasource": {
            "type": "influxdb",
            "uid": "B87265B08D314AF"
          },
          "query": "from(bucket: \"${bucket}\")\n  |\u003e range(start: v.timeRangeStart, stop: v.timeRangeStop)\n  |\u003e filter(fn: (r) =\u003e r[\"_measurement\"] == \"validator_performance\")\n  |\u003e filter(fn: (r) =\u003e r[\"validator_address\"] == \"${validator}\")\n  |\u003e group(columns: [\"_field\"])\n  |\u003e aggregateWindow(every: 10m, fn: mean, createEmpty: false)"
        }
      ],
      "title": "Validator Performance",
      "description": "Performance metrics timeline for the selected validator",
      "transparent": false,
      "datasource": {
        "type": "influxdb",
        "uid": "B87265B08D314AF"
      },
      "gridPos": {
        "h": 9,
        "w": 12,
        "x": 12,
        "y": 11
      },
      "fieldConfig": {
        "defaults": {
          "unit": "percent"
        },
        "overrides": null
      }
    },
    {
      "type": "timeseries",
      "targets": [
        {
          "refId": "A",
          "queryType": "flux",
          "datasource": {
            "type": "influxdb",
            "uid": "B87265B08D314AF"
          },
          "query": "from(bucket: \"${bucket}\")\n  |\u003e range(start: v.timeRangeStart, stop: v.timeRangeStop)\n  |\u003e filter(fn: (r) =\u003e r[\"_measurement\"] == \"recent_slots\")\n  |\u003e filter(fn: (r) =\u003e r[\"proposer\"] == \"${validator}\")\n  |\u003e group(columns: [\"filled\"])\n  |\u003e aggregateWindow(every: 30m, fn: count, createEmpty: false)"
        }
      ],
      "title": "Block Production",
      "description": "Block production activity for the selected validator",
      "transparent": false,
      "datasource": {
        "type": "influxdb",
        "uid": "B87265B08D314AF"
      },
      "gridPos": {
        "h": 9,
        "w": 12,
        "x": 0,
        "y": 20
      },
      "fieldConfig": {
        "defaults": {
          "unit": "short"
        },
        "overrides": null
      }
    },
    {
      "type": "timeseries",
      "targets": [
        {
          "refId": "A",
          "queryType": "flux",
          "datasource": {
            "type": "influxdb",
            "uid": "B87265B08D314AF"
          },
          "query": "from(bucket: \"${bucket}\")\n  |\u003e range(start: v.timeRangeStart, stop: v.timeRangeStop)\n  |\u003e filter(fn: (r) =\u003e r[\"_measurement\"] == \"validator_rewards\")\n  |\u003e filter(fn: (r) =\u003e r[\"validator_address\"] == \"${validator}\")\n  |\u003e group(columns: [\"reward_type\"])\n  |\u003e aggregateWindow(every: 1h, fn: sum, createEmpty: false)"
        }
      ],
      "title": "Rewards Distribution",
      "description": "Rewards earned and distributed by this validator",
      "transparent": false,
      "datasource": {
        "type": "influxdb",
        "uid": "B87265B08D314AF"
      },
      "gridPos": {
        "h": 9,
        "w": 12,
        "x": 12,
        "y": 20
      },
      "fieldConfig": {
        "defaults": {
          "unit": "short"
        },
        "overrides": null
      }
    },
    {
      "type": "table",
      "targets": [
        {
          "refId": "A",
          "queryType": "flux",
          "datasource": {
            "type": "influxdb",
            "uid": "B87265B08D314AF"
          },
          "query": "from(bucket: \"${bucket}\")\n  |\u003e range(start: v.timeRangeStart, stop: v.timeRangeStop)\n  |\u003e filter(fn: (r) =\u003e r[\"_measurement\"] == \"validator_delegations\")\n  |\u003e filter(fn: (r) =\u003e r[\"validator_address\"] == \"${validator}\")\n  |\u003e group(columns: [\"delegator_address\"])\n  |\u003e last()\n  |\u003e group()\n  |\u003e sort(columns: [\"_value\"], desc: true)\n  |\u003e limit(n: 20)"
        }
      ],
      "title": "Top Delegators",
      "description": "Table showing the top delegators for this validator",
      "transparent": false,
      "datasource": {
        "type": "influxdb",
        "uid": "B87265B08D314AF"
      },
      "gridPos": {
        "h": 9,
        "w": 12,
        "x": 0,
        "y": 29
      }
    }
  ],
  "templating": {
    "list": [
      {
        "type": "query",
        "name": "bucket",
        "label": "Bucket",
        "hide": 0,
        "skipUrlSync": false,
        "query": "buckets()",
        "datasource": {
          "type": "influxdb",
          "uid": "B87265B08D314AF"
        },
        "current": {
          "selected": false,
          "text": "mainnet",
          "value": "mainnet"
        },
        "multi": false,
        "refresh": 2,
        "includeAll": false,
        "auto": false,
        "auto_min": "10s",
        "auto_count": 30
      },
      {
        "type": "query",
        "name": "validator",
        "label": "Validator",
        "hide": 0,
        "skipUrlSync": false,
        "query": "import \"influxdata/influxdb/schema\"\n\nschema.tagValues(bucket: \"${bucket}\", tag: \"validator_address\")",
        "datasource": {
          "type": "influxdb",
          "uid": "B87265B08D314AF"
        },
        "current": {
          "selected": false,
          "text": "",
          "value": ""
        },
        "multi": false,
        "refresh": 2,
        "includeAll": false,
        "auto": false,
        "auto_min": "10s",
        "auto_count": 30
      }
    ]
  },
  "annotations": {}
}